pushikoo_pusher_dingtalk/__init__.py
pushikoo_pusher_dingtalk/api.py
pushikoo_pusher_dingtalk/config.py
pushikoo_pusher_dingtalk/main.py
pushikoo_pusher_dingtalk-0.2.1.dist-info/METADATA
pushikoo_pusher_dingtalk-0.2.1.dist-info/WHEEL
pushikoo_pusher_dingtalk-0.2.1.dist-info/entry_points.txt
pushikoo_pusher_dingtalk-0.2.1.dist-info/licenses/LICENSE
pushikoo_pusher_dingtalk-0.2.1.dist-info/RECORD
