Metadata-Version: 2.4
Name: pushikoo-pusher-dingtalk
Version: 0.2.1
Summary: DingTalk custom bot pusher for Pushikoo.
Project-URL: Homepage, https://github.com/Pushikoo/pushikoo-pusher-dingtalk
Author: Pushikoo
License-File: LICENSE
Classifier: Operating System :: OS Independent
Classifier: Programming Language :: Python :: 3
Requires-Python: >=3.10
Requires-Dist: boto3
Requires-Dist: loguru
Requires-Dist: pushikoo-interface>=1.0.0
Requires-Dist: requests
Provides-Extra: dev
Requires-Dist: pytest; extra == 'dev'
Requires-Dist: ruff; extra == 'dev'
